cuda2mlu/__init__.py
cuda2mlu/torch_proxy.py
cuda2mlu-0.1.dist-info/METADATA
cuda2mlu-0.1.dist-info/WHEEL
cuda2mlu-0.1.dist-info/top_level.txt
cuda2mlu-0.1.dist-info/RECORD
