Metadata-Version: 2.1
Name: cuda2mlu
Version: 0.1
Summary: A package that rewrites torch device CUDA  to use MLU
Home-page: UNKNOWN
License: UNKNOWN
Platform: UNKNOWN
Requires-Python: >=3.6
Requires-Dist: torch
